pyjoulescope_driver/__init__.py
pyjoulescope_driver/__main__.py
pyjoulescope_driver/binding.c
pyjoulescope_driver/binding.cpython-314-aarch64-linux-gnu.so
pyjoulescope_driver/img_alpha.img
pyjoulescope_driver/img_beta.img
pyjoulescope_driver/img_stable.img
pyjoulescope_driver/program.py
pyjoulescope_driver/record.py
pyjoulescope_driver/release.py
pyjoulescope_driver/time64.py
pyjoulescope_driver/version.py
pyjoulescope_driver/entry_points/__init__.py
pyjoulescope_driver/entry_points/api_timeout.py
pyjoulescope_driver/entry_points/gpi.py
pyjoulescope_driver/entry_points/info.py
pyjoulescope_driver/entry_points/measure.py
pyjoulescope_driver/entry_points/program.py
pyjoulescope_driver/entry_points/record.py
pyjoulescope_driver/entry_points/scan.py
pyjoulescope_driver/entry_points/set_parameter.py
pyjoulescope_driver/entry_points/statistics.py
pyjoulescope_driver/entry_points/threads.py
pyjoulescope_driver/test/__init__.py
pyjoulescope_driver/test/test_calibration_hash.py
pyjoulescope_driver/test/test_release.py
pyjoulescope_driver/test/test_time64.py
pyjoulescope_driver/test/release/__init__.py
pyjoulescope_driver/test/release/index.html
pyjoulescope_driver/test/release/index.json
pyjoulescope_driver/test/release/ctrl_app/__init__.py
pyjoulescope_driver/test/release/ctrl_app/index.html
pyjoulescope_driver/test/release/ctrl_app/index.json
pyjoulescope_driver/test/release/ctrl_app/js220_ctrl_app_1_0_1.img
pyjoulescope_driver/test/release/ctrl_app/js220_ctrl_app_1_0_1_CHANGELOG.md
pyjoulescope_driver/test/release/ctrl_updater1/__init__.py
pyjoulescope_driver/test/release/ctrl_updater1/index.html
pyjoulescope_driver/test/release/ctrl_updater1/index.json
pyjoulescope_driver/test/release/ctrl_updater1/js220_ctrl_updater1_1_0_1.img
pyjoulescope_driver/test/release/ctrl_updater1/js220_ctrl_updater1_1_0_1_CHANGELOG.md
pyjoulescope_driver/test/release/ctrl_updater2/__init__.py
pyjoulescope_driver/test/release/ctrl_updater2/index.html
pyjoulescope_driver-1.12.0.dist-info/METADATA
pyjoulescope_driver-1.12.0.dist-info/WHEEL
pyjoulescope_driver-1.12.0.dist-info/entry_points.txt
pyjoulescope_driver-1.12.0.dist-info/top_level.txt
pyjoulescope_driver-1.12.0.dist-info/RECORD
pyjoulescope_driver-1.12.0.dist-info/licenses/LICENSE.txt
pyjoulescope_driver-1.12.0.dist-info/sboms/auditwheel.cdx.json
